argi/__init__.py
argi/argi.py
argi-0.2.44.dist-info/LICENSE
argi-0.2.44.dist-info/METADATA
argi-0.2.44.dist-info/WHEEL
argi-0.2.44.dist-info/top_level.txt
argi-0.2.44.dist-info/RECORD
