Metadata-Version: 2.1
Name: argi
Version: 0.2.44
Summary: graph dimension reduction using timeseries
Home-page: https://github.com/trakuo/argi
Author: Sergio Iglesias
Author-email: trakuo@gmail.com
License: UNKNOWN
Platform: UNKNOWN
Classifier: Programming Language :: Python :: 3
Classifier: License :: OSI Approved :: MIT License
Classifier: Operating System :: OS Independent
